payok/__init__.py
payok/api.py
payok/exceptions.py
payok/enums/__init__.py
payok/enums/base.py
payok/enums/comission_type.py
payok/enums/currency.py
payok/enums/pay_status.py
payok/enums/payment_method.py
payok/enums/payout_method.py
payok/enums/webhook_status.py
payok/models/__init__.py
payok/models/balance.py
payok/models/new_payout.py
payok/models/payout.py
payok/models/transaction.py
payok.io-1.0.7.dist-info/LICENSE
payok.io-1.0.7.dist-info/METADATA
payok.io-1.0.7.dist-info/WHEEL
payok.io-1.0.7.dist-info/top_level.txt
payok.io-1.0.7.dist-info/RECORD
