Metadata-Version: 2.1
Name: payok.io
Version: 1.0.7
Summary: Asynchronous PayOK API wrapper
Home-page: https://github.com/nikitalm8/payok
Author: Nikita Minaev
Author-email: <nikita@minaev.su>
Project-URL: Homepage, https://github.com/nikitalm8/payok
Project-URL: Bug Tracker, https://github.com/nikitalm8/payok/issues
Project-URL: API Docs, https://payok.io/cabinet/documentation/doc_api_main
Keywords: python,payok.io,payments,payok-api,async,asyncio
Classifier: Development Status :: 4 - Beta
Classifier: Intended Audience :: Developers
Classifier: Programming Language :: Python :: 3
Classifier: Operating System :: Unix
Classifier: Operating System :: MacOS :: MacOS X
Classifier: Operating System :: Microsoft :: Windows
License-File: LICENSE
Requires-Dist: aiohttp
Requires-Dist: pydantic
